[
    {
        "url": "http://ai.suishoubang.com/upload/images/chezhu/che/aodiA6L.png",
        "type": "奥迪A6L2024款45 TFSI quattro 尊享动感型",
        "color": "暂无"
    },
    {
        "url": "http://ai.suishoubang.com/upload/images/chezhu/che/aodiA4L.png",
        "type": "奥迪A4L2023款40 TFSI 豪华动感型",
        "color": "暂无"
    },
    {
        "url": "http://ai.suishoubang.com/upload/images/chezhu/che/benzE300L.png",
        "type": "奔驰E2024款E 300 L 时尚型 运动轿车",
        "color": "暂无"
    },
    {
        "url": "http://ai.suishoubang.com/upload/images/chezhu/che/benzC260L.png",
        "type": "奔驰C2024款改款 C 260 L 运动版",
        "color": "暂无"
    },
    {
        "url": "http://ai.suishoubang.com/upload/images/chezhu/che/bmw530Li.png",
        "type": "宝马5系2023款530Li 尊享型 M运动套装",
        "color": "暂无"
    },
    {
        "url": "http://ai.suishoubang.com/upload/images/chezhu/che/bmw330Li.png",
        "type": "宝马3系2023款330Li M运动曜夜套装",
        "color": "暂无"
    },
    {
        "url": "http://p9-dcd.byteimg.com/img/motor-mis-img/02496c32796d3a514fdc24ab7c23f8d1~tplv-resize:1200:0.webp",
        "type": "指南者2017款200T 自动臻享版",
        "color": "皓白"
    },
    {
        "url": "http://p3-dcd.byteimg.com/img/motor-mis-img/9766a40f92d9065d84a2949fbfed8881~tplv-resize:1200:0.webp",
        "type": "自由侠2017款180T 自动智能版",
        "color": "烈焰橙"
    },
    {
        "url": "http://p9-dcd.byteimg.com/img/motor-mis-img/4dffb197fea295977d1fe75a024be315~tplv-resize:1200:0.webp",
        "type": "Panamera E-Hybrid2017款Panamera 4 E-Hybrid 行政加长版 2.9T",
        "color": "黑色"
    },
    {
        "url": "http://p3-dcd.byteimg.com/img/motor-mis-img/e13c4860d848f493ad6b0b12293a5fa2~tplv-resize:1200:0.webp",
        "type": "北汽新能源EC2017款EC180 灵秀版",
        "color": "爱琴海蓝"
    },
    {
        "url": "http://p9-dcd.byteimg.com/img/motor-mis-img/a600f03c4a86ce899e854f8102db68ca~tplv-resize:1200:0.webp",
        "type": "北汽新能源EU2017款EU260 乐途plus版",
        "color": "熔岩红"
    },
    {
        "url": "http://p9-dcd.byteimg.com/img/motor-mis-img/234a0775afcac9baeb354f6912383763~tplv-resize:1200:0.webp",
        "type": "奔驰A级AMG(进口)2017款AMG A 45 4MATIC",
        "color": "卷云白"
    },
    {
        "url": "http://p6-dcd.byteimg.com/img/motor-mis-img/b2f0d5f2da36ff477c5092be6152a958~tplv-resize:1200:0.webp",
        "type": "奔驰E级2017款E 320 L 4MATIC",
        "color": "北极白"
    },
    {
        "url": "http://p1-dcd.byteimg.com/img/motor-mis-img/7fa833a5aca27b979f9c4d823899cf6a~tplv-resize:1200:0.webp",
        "type": "奔驰GLC2017款GLC 300 4MATIC 豪华型",
        "color": "北极白"
    },
    {
        "url": "http://p6-dcd.byteimg.com/img/motor-mis-img/f2aed98855298bc7041eb5009526c12c~tplv-resize:1200:0.webp",
        "type": "奔驰GLE轿跑2017款GLE 400 4MATIC 轿跑SUV",
        "color": "北极白"
    },
    {
        "url": "http://p1-dcd.byteimg.com/img/motor-mis-img/3a9f13a5768b4b987863a39bae58a0a6~tplv-resize:1200:0.webp",
        "type": "奔驰SL级2017款SL 400",
        "color": "锆石英红"
    },
    {
        "url": "http://p6-dcd.byteimg.com/img/motor-mis-img/ec5100687f06b1cdd2d932c39745bf37~tplv-resize:1200:0.webp",
        "type": "奔驰S级2017款S 500 4MATIC 轿跑版",
        "color": "月光石灰"
    },
    {
        "url": "http://p1-dcd.byteimg.com/img/motor-mis-img/2f0e71195c82e58b9be9ab65cc08b258~tplv-resize:1200:0.webp",
        "type": "奥德赛2017款2.4L 至尊福祉版",
        "color": "星空蓝"
    },
    {
        "url": "http://p9-dcd.byteimg.com/img/motor-mis-img/42341d2a603805f69d981c89900b2ea3~tplv-resize:1200:0.webp",
        "type": "本田XR-V2017款1.8L EXi CVT舒适版",
        "color": "彩晶黑"
    },
    {
        "url": "http://p6-dcd.byteimg.com/img/motor-mis-img/176a079f7535ebcd5aa399272cafc7f6~tplv-resize:1200:0.webp",
        "type": "冠道2017款370TURBO 四驱至尊版",
        "color": "奥夫特黑"
    },
    {
        "url": "http://p9-dcd.byteimg.com/img/motor-mis-img/bbd3276c9dab4b48e3a4edd5fa1e7425~tplv-resize:1200:0.webp",
        "type": "竞瑞2017款1.5L CVT经典版",
        "color": "璀璨紫"
    },
    {
        "url": "http://p6-dcd.byteimg.com/img/motor-mis-img/349d0292e4b3c108a582b95db4f19e35~tplv-resize:1200:0.webp",
        "type": "比速M32017款1.5L 尊享型",
        "color": "朱砂红"
    },
    {
        "url": "http://p6-dcd.byteimg.com/img/motor-mis-img/26b16b1fe9c1c737dcf02acd4b2e1e07~tplv-resize:1200:0.webp",
        "type": "别克GL82017款28T Avenir 国V",
        "color": "伯爵紫"
    },
    {
        "url": "http://p1-dcd.byteimg.com/img/motor-mis-img/28798ceab943f5d5f0c0a488485cccd1~tplv-resize:1200:0.webp",
        "type": "慕尚2017款6.8T 长轴距版",
        "color": "Anthracite"
    },
    {
        "url": "http://p1-dcd.byteimg.com/img/motor-mis-img/6518c213f9e25d332f3feff8c1040151~tplv-resize:1200:0.webp",
        "type": "捷达2017款1.5L 手动舒适型",
        "color": "甜蜜金"
    },
    {
        "url": "http://p3-dcd.byteimg.com/img/motor-mis-img/c43041f5b5c5859d569dba3dc253a0fa~tplv-resize:1200:0.webp",
        "type": "帕萨特2017款330TSI DSG尊荣版",
        "color": "玉白"
    },
    {
        "url": "http://p6-dcd.byteimg.com/img/motor-mis-img/3c3169e8c3928539e61e291f840fd5b6~tplv-resize:1200:0.webp",
        "type": "途观2017款300TSI 自动两驱丝绸之路舒适版",
        "color": "极光白"
    },
    {
        "url": "http://p3-dcd.byteimg.com/img/motor-mis-img/4d20f8e22df9511951316ca5bf768d9d~tplv-resize:1200:0.webp",
        "type": "风行S5002017款1.5L 手动豪华型",
        "color": "珍珠白"
    },
    {
        "url": "http://p9-dcd.byteimg.com/img/motor-mis-img/fda9d2e71a4267e58ee186ca2c34b415~tplv-resize:1200:0.webp",
        "type": "福克斯2017款两厢 EcoBoost 180 自动运动型",
        "color": "星河银"
    },
    {
        "url": "http://p6-dcd.byteimg.com/img/motor-mis-img/dd9af3abffab6a393850d8d5ff98ed05~tplv-resize:1200:0.webp",
        "type": "蒙迪欧2017款EcoBoost 245 旗舰型",
        "color": "典雅白"
    },
    {
        "url": "http://p1-dcd.byteimg.com/img/motor-mis-img/007783ded36f6784fc4f2ced5f877ad8~tplv-resize:1200:0.webp",
        "type": "探险者(进口)2017款2.3T 精英版",
        "color": "珍珠岩白"
    },
    {
        "url": "http://p9-dcd.byteimg.com/img/motor-mis-img/33fdf51bd30eb96d914fa0e141d2199a~tplv-resize:1200:0.webp",
        "type": "翼虎2017款EcoBoost 245 四驱尊翼型",
        "color": "峡谷棕"
    },
    {
        "url": "http://p3-dcd.byteimg.com/img/motor-mis-img/9aee757bd1880538616cf7f0717b594a~tplv-resize:1200:0.webp",
        "type": "传祺GS82017款320T 两驱豪华智联版 7座",
        "color": "典雅黑"
    },
    {
        "url": "http://p9-dcd.byteimg.com/img/motor-mis-img/912e22a77fef0742dcf76096bb079b42~tplv-resize:1200:0.webp",
        "type": "海马S72017款1.8T 自动豪华版",
        "color": "极地白"
    },
    {
        "url": "http://p9-dcd.byteimg.com/img/motor-mis-img/6db7095213add482311c1c030e446adb~tplv-resize:1200:0.webp",
        "type": "凯迪拉克ATS-L2017款28T 领先型",
        "color": "霓虹"
    },
    {
        "url": "http://p6-dcd.byteimg.com/img/motor-mis-img/cf158d5c2414d5d8d63c71e11214ad03~tplv-resize:1200:0.webp",
        "type": "揽胜星脉2017款P380 R-DYNAMIC HSE",
        "color": "富士白"
    },
    {
        "url": "http://p1-dcd.byteimg.com/img/motor-mis-img/356648ed8c7be7d7355969b5e1c42e48~tplv-resize:1200:0.webp",
        "type": "马自达3 昂克赛拉2017款两厢 2.0L 自动运动型 国V",
        "color": "珠光白"
    },
    {
        "url": "http://p6-dcd.byteimg.com/img/motor-mis-img/dc3f2722e801c8a873c22f6eb7c59b36~tplv-resize:1200:0.webp",
        "type": "起亚K22017款三厢 1.4L AT GLS",
        "color": "碧海蓝"
    },
    {
        "url": "http://p1-dcd.byteimg.com/img/motor-mis-img/cf3a575f25d588f578dd9ee5a28fa76d~tplv-resize:1200:0.webp",
        "type": "起亚KX72017款2.0T 自动两驱GLS 7座",
        "color": "大漠金"
    },
    {
        "url": "http://p1-dcd.byteimg.com/img/motor-mis-img/ade1e41dc4cdf5fc913f39acaa2ca604~tplv-resize:1200:0.webp",
        "type": "楼兰2017款2.5 S/C HEV XL 四驱混动尊贵版",
        "color": "珠光白"
    },
    {
        "url": "http://p3-dcd.byteimg.com/img/motor-mis-img/dc2622206455c5cb5341623e5ecd7901~tplv-resize:1200:0.webp",
        "type": "晶锐2017款1.4L 自动前行版",
        "color": "爵士白"
    },
    {
        "url": "http://p9-dcd.byteimg.com/img/motor-mis-img/e9e7ea8350bd4e2f9ca6d20a248462ff~tplv-resize:1200:0.webp",
        "type": "沃尔沃S60(进口)2017款2.0T Polestar",
        "color": "冰雪白"
    },
    {
        "url": "http://p6-dcd.byteimg.com/img/motor-mis-img/42b89a50f60642a265186ac5fbaa2f3d~tplv-resize:1200:0.webp",
        "type": "沃尔沃V602017款Cross Country T5 AWD 国V",
        "color": "水晶白"
    },
    {
        "url": "http://p6-dcd.byteimg.com/img/motor-mis-img/4fd3a090a83f596f2423ccbb2a9f3613~tplv-resize:1200:0.webp",
        "type": "胜达2017款2.4L 自动两驱智能型 5座",
        "color": "幻影黑"
    },
    {
        "url": "http://p6-dcd.byteimg.com/img/motor-mis-img/8aa76c47d2ca68f08ac96065d8cb7ea1~tplv-resize:1200:0.webp",
        "type": "科鲁兹2017款1.4T 双离合领锋版",
        "color": "极光白"
    },
    {
        "url": "http://p1-dcd.byteimg.com/img/motor-mis-img/5b61cf00d8225b1d1526b3d9323190f0~tplv-resize:1200:0.webp",
        "type": "科迈罗2017款2.0T RS",
        "color": "耀黑"
    },
    {
        "url": "http://p9-dcd.byteimg.com/img/motor-mis-img/ec385b6ba98803311a02b838c932cb1a~tplv-resize:1200:0.webp",
        "type": "英菲尼迪QX302017款1.6T 两驱时尚版",
        "color": "莹贝白"
    },
    {
        "url": "http://p3-dcd.byteimg.com/img/motor-mis-img/f6de3233e1c928684e437ac517c7f8ec~tplv-resize:1200:0.webp",
        "type": "长安CS752017款尚酷版 1.8T 自动四驱尊贵型",
        "color": "精灵白"
    },
    {
        "url": "http://p6-dcd.byteimg.com/img/motor-mis-img/5e404ab3c1aa6a4e9bcb52b2474c3f9f~tplv-resize:1200:0.webp",
        "type": "长安CS952017款2.0T 四驱智尊版",
        "color": "安第斯灰"
    },
    {
        "url": "http://p3-dcd.byteimg.com/img/motor-mis-img/5b472d2fc82b1ad46f7334a5880f029d~tplv-resize:1200:0.webp",
        "type": "中华H32017款1.5L 手动精英型",
        "color": "灵动红"
    }
]